{
	"archive" : {},
	"artifacts" : 
	[
		{
			"path" : "rnnoise/librnnoise.a"
		}
	],
	"backtrace" : 1,
	"backtraceGraph" : 
	{
		"commands" : 
		[
			"add_library",
			"install",
			"include_directories"
		],
		"files" : 
		[
			"rnnoise/CMakeLists.txt",
			"CMakeLists.txt"
		],
		"nodes" : 
		[
			{
				"file" : 0
			},
			{
				"command" : 0,
				"file" : 0,
				"line" : 7,
				"parent" : 0
			},
			{
				"command" : 1,
				"file" : 0,
				"line" : 24,
				"parent" : 0
			},
			{
				"file" : 1
			},
			{
				"command" : 2,
				"file" : 1,
				"line" : 9,
				"parent" : 3
			},
			{
				"command" : 2,
				"file" : 0,
				"line" : 5,
				"parent" : 0
			},
			{
				"command" : 2,
				"file" : 0,
				"line" : 6,
				"parent" : 0
			}
		]
	},
	"compileGroups" : 
	[
		{
			"compileCommandFragments" : 
			[
				{
					"fragment" : "-g  "
				},
				{
					"fragment" : "-std=gnu99"
				}
			],
			"includes" : 
			[
				{
					"backtrace" : 4,
					"path" : "/mnt/s/UpworkProjects/DavidAGC/finalCode/rnnoise"
				},
				{
					"backtrace" : 5,
					"path" : "/mnt/s/UpworkProjects/DavidAGC/finalCode/rnnoise/include"
				},
				{
					"backtrace" : 6,
					"path" : "/mnt/s/UpworkProjects/DavidAGC/finalCode/rnnoise/src"
				}
			],
			"language" : "C",
			"sourceIndexes" : 
			[
				0,
				1,
				2,
				3,
				4,
				5,
				6,
				7,
				8,
				9,
				10,
				11,
				12
			]
		}
	],
	"id" : "rnnoise::@51c249f08d48b9ae4572",
	"install" : 
	{
		"destinations" : 
		[
			{
				"backtrace" : 2,
				"path" : "lib"
			}
		],
		"prefix" : 
		{
			"path" : "/usr/local"
		}
	},
	"name" : "rnnoise",
	"nameOnDisk" : "librnnoise.a",
	"paths" : 
	{
		"build" : "rnnoise",
		"source" : "rnnoise"
	},
	"sourceGroups" : 
	[
		{
			"name" : "Source Files",
			"sourceIndexes" : 
			[
				0,
				1,
				2,
				3,
				4,
				5,
				6,
				7,
				8,
				9,
				10,
				11,
				12
			]
		}
	],
	"sources" : 
	[
		{
			"backtrace" : 1,
			"compileGroupIndex" : 0,
			"path" : "rnnoise/src/celt_lpc.c",
			"sourceGroupIndex" : 0
		},
		{
			"backtrace" : 1,
			"compileGroupIndex" : 0,
			"path" : "rnnoise/src/denoise.c",
			"sourceGroupIndex" : 0
		},
		{
			"backtrace" : 1,
			"compileGroupIndex" : 0,
			"path" : "rnnoise/src/kiss_fft.c",
			"sourceGroupIndex" : 0
		},
		{
			"backtrace" : 1,
			"compileGroupIndex" : 0,
			"path" : "rnnoise/src/models.c",
			"sourceGroupIndex" : 0
		},
		{
			"backtrace" : 1,
			"compileGroupIndex" : 0,
			"path" : "rnnoise/src/pitch.c",
			"sourceGroupIndex" : 0
		},
		{
			"backtrace" : 1,
			"compileGroupIndex" : 0,
			"path" : "rnnoise/src/rnn.c",
			"sourceGroupIndex" : 0
		},
		{
			"backtrace" : 1,
			"compileGroupIndex" : 0,
			"path" : "rnnoise/src/rnn_data.c",
			"sourceGroupIndex" : 0
		},
		{
			"backtrace" : 1,
			"compileGroupIndex" : 0,
			"path" : "rnnoise/src/rnn_reader.c",
			"sourceGroupIndex" : 0
		},
		{
			"backtrace" : 1,
			"compileGroupIndex" : 0,
			"path" : "rnnoise/src/models/bd.c",
			"sourceGroupIndex" : 0
		},
		{
			"backtrace" : 1,
			"compileGroupIndex" : 0,
			"path" : "rnnoise/src/models/cb.c",
			"sourceGroupIndex" : 0
		},
		{
			"backtrace" : 1,
			"compileGroupIndex" : 0,
			"path" : "rnnoise/src/models/lq.c",
			"sourceGroupIndex" : 0
		},
		{
			"backtrace" : 1,
			"compileGroupIndex" : 0,
			"path" : "rnnoise/src/models/mp.c",
			"sourceGroupIndex" : 0
		},
		{
			"backtrace" : 1,
			"compileGroupIndex" : 0,
			"path" : "rnnoise/src/models/sh.c",
			"sourceGroupIndex" : 0
		}
	],
	"type" : "STATIC_LIBRARY"
}
